fdwm/__init__.py
fdwm/__main__.py
fdwm/cli.py
fdwm/watermark.py
fdwm-0.2.2.dist-info/licenses/LICENSE
fdwm-0.2.2.dist-info/METADATA
fdwm-0.2.2.dist-info/WHEEL
fdwm-0.2.2.dist-info/entry_points.txt
fdwm-0.2.2.dist-info/top_level.txt
fdwm-0.2.2.dist-info/RECORD
