Metadata-Version: 2.4
Name: fdwm
Version: 0.2.2
Summary: Frequency-domain watermarking library and CLI
Home-page: https://github.com/Liam0205/fdwm
Author: Liam Huang
Author-email: Liam Huang <PyPI@liam.page>
Maintainer-email: Liam Huang <PyPI@liam.page>
License-Expression: MIT
Project-URL: Homepage, https://github.com/Liam0205/fdwm
Project-URL: Repository, https://github.com/Liam0205/fdwm
Project-URL: Documentation, https://github.com/Liam0205/fdwm#readme
Project-URL: Bug Tracker, https://github.com/Liam0205/fdwm/issues
Keywords: watermark,steganography,image processing,frequency domain,fft
Classifier: Development Status :: 4 - Beta
Classifier: Intended Audience :: Developers
Classifier: Operating System :: OS Independent
Classifier: Programming Language :: Python :: 3
Classifier: Programming Language :: Python :: 3.10
Classifier: Programming Language :: Python :: 3.11
Classifier: Programming Language :: Python :: 3.12
Classifier: Programming Language :: Python :: 3.13
Classifier: Topic :: Multimedia :: Graphics
Classifier: Topic :: Scientific/Engineering :: Image Processing
Classifier: Topic :: Security :: Cryptography
Requires-Python: >=3.10
License-File: LICENSE
Requires-Dist: numpy>=1.20
Requires-Dist: opencv-python>=4.5
Requires-Dist: Pillow>=10.0
Requires-Dist: pytesseract>=0.3.10
Provides-Extra: dev
Requires-Dist: pytest>=6.0; extra == "dev"
Requires-Dist: pytest-cov>=4.0; extra == "dev"
Requires-Dist: black>=22.0; extra == "dev"
Requires-Dist: flake8>=4.0; extra == "dev"
Requires-Dist: isort>=5.0; extra == "dev"
Requires-Dist: mypy>=1.0; extra == "dev"
Dynamic: author
Dynamic: home-page
Dynamic: license-file
Dynamic: requires-python
